reservoirpy/__init__.py
reservoirpy/_base.py
reservoirpy/_version.py
reservoirpy/activationsfunc.py
reservoirpy/mat_gen.py
reservoirpy/model.py
reservoirpy/node.py
reservoirpy/observables.py
reservoirpy/ops.py
reservoirpy/type.py
reservoirpy/compat/__init__.py
reservoirpy/compat/_base.py
reservoirpy/compat/_esn.py
reservoirpy/compat/_esn_online.py
reservoirpy/compat/regression_models.py
reservoirpy/compat/tests/__init__.py
reservoirpy/compat/tests/test_esn.py
reservoirpy/compat/tests/test_esnonline.py
reservoirpy/compat/tests/test_load_from_previous_versions.py
reservoirpy/compat/tests/test_regression_models.py
reservoirpy/compat/tests/test_validation.py
reservoirpy/compat/utils/__init__.py
reservoirpy/compat/utils/parallel.py
reservoirpy/compat/utils/save.py
reservoirpy/compat/utils/validation.py
reservoirpy/datasets/__init__.py
reservoirpy/datasets/_chaos.py
reservoirpy/datasets/_japanese_vowels.py
reservoirpy/datasets/_seed.py
reservoirpy/datasets/_utils.py
reservoirpy/datasets/tests/__init__.py
reservoirpy/datasets/tests/test_datasets.py
reservoirpy/experimental/__init__.py
reservoirpy/experimental/add.py
reservoirpy/experimental/batchforce.py
reservoirpy/experimental/norm.py
reservoirpy/experimental/randomchoice.py
reservoirpy/experimental/sklearn.py
reservoirpy/experimental/gpu/__init__.py
reservoirpy/experimental/tests/__init__.py
reservoirpy/hyper/__init__.py
reservoirpy/hyper/_hyperplot.py
reservoirpy/hyper/_hypersearch.py
reservoirpy/nodes/__init__.py
reservoirpy/nodes/activations.py
reservoirpy/nodes/concat.py
reservoirpy/nodes/esn.py
reservoirpy/nodes/io.py
reservoirpy/nodes/readouts/__init__.py
reservoirpy/nodes/readouts/base.py
reservoirpy/nodes/readouts/force.py
reservoirpy/nodes/readouts/lms.py
reservoirpy/nodes/readouts/ridge.py
reservoirpy/nodes/readouts/rls.py
reservoirpy/nodes/reservoirs/__init__.py
reservoirpy/nodes/reservoirs/base.py
reservoirpy/nodes/reservoirs/intrinsic_plasticity.py
reservoirpy/nodes/reservoirs/nvar.py
reservoirpy_fbessou-0.3.13.dist-info/LICENSE
reservoirpy_fbessou-0.3.13.dist-info/METADATA
reservoirpy_fbessou-0.3.13.dist-info/WHEEL
reservoirpy_fbessou-0.3.13.dist-info/top_level.txt
reservoirpy_fbessou-0.3.13.dist-info/RECORD
