Metadata-Version: 2.1
Name: reservoirpy-fbessou
Version: 0.3.13
Summary: A simple and flexible code for Reservoir Computing architectures like Echo State Networks.
Home-page: https://github.com/reservoirpy/reservoirpy
Download-URL: https://github.com/reservoirpy/reservoirpy/v0.3.13.tar.gz
Author: Xavier Hinaut
Author-email: xavier.hinaut@inria.fr
Maintainer: Xavier Hinaut, Nathan Trouvain
Maintainer-email: xavier.hinaut@inria.fr, nathan.trouvain@inria.fr
Project-URL: Bug Tracker, https://github.com/reservoirpy/reservoirpy/issues
Project-URL: Documentation, https://reservoirpy.readthedocs.io/en/latest/index.html
Project-URL: Source Code, https://github.com/reservoirpy/reservoirpy
Classifier: Intended Audience :: Science/Research
Classifier: Intended Audience :: Developers
Classifier: License :: OSI Approved :: MIT License
Classifier: Programming Language :: Python
Classifier: Topic :: Scientific/Engineering
Classifier: Topic :: Scientific/Engineering :: Artificial Intelligence
Classifier: Operating System :: Microsoft :: Windows
Classifier: Operating System :: POSIX
Classifier: Operating System :: Unix
Classifier: Operating System :: MacOS
Classifier: Operating System :: OS Independent
Classifier: Programming Language :: Python :: 3
Classifier: Programming Language :: Python :: 3.6
Classifier: Programming Language :: Python :: 3.7
Classifier: Programming Language :: Python :: 3.8
Classifier: Programming Language :: Python :: 3.9
Classifier: Programming Language :: Python :: Implementation :: PyPy
Requires-Python: >=3.6
License-File: LICENSE
Requires-Dist: tqdm (>=4.43.0)
Requires-Dist: joblib (>=0.12)
Requires-Dist: dill (>=0.3.0)
Requires-Dist: numpy (>=1.21.1)
Requires-Dist: scipy (<=1.7.3,>=1.0.0)
Provides-Extra: hyper
Requires-Dist: matplotlib (>=2.2.0) ; extra == 'hyper'
Requires-Dist: hyperopt ; extra == 'hyper'
Requires-Dist: seaborn ; extra == 'hyper'
